missioncontrolbot-0.1.1.dist-info/METADATA
missioncontrolbot-0.1.1.dist-info/WHEEL
missioncontrolbot-0.1.1.dist-info/entry_points.txt
missioncontrolbot/__init__.py
missioncontrolbot/cli.py
missioncontrolbot/missioncontrolbot.py
missioncontrolbot/openai/terminal_tester.py
missioncontrolbot-0.1.1.dist-info/RECORD
